pytest_aux/__init__.py
pytest_aux/main.py
pytest_aux-0.1.13.dist-info/LICENSE
pytest_aux-0.1.13.dist-info/METADATA
pytest_aux-0.1.13.dist-info/WHEEL
pytest_aux-0.1.13.dist-info/top_level.txt
pytest_aux-0.1.13.dist-info/RECORD
